siphono_notify/__init__.py
siphono_notify/client.py
siphono_notify/configs.py
siphono_notify/notifier.py
siphono_notify/progress_bar.py
siphono_notify/target.py
siphono_notify-0.1.0.dist-info/WHEEL
siphono_notify-0.1.0.dist-info/METADATA
siphono_notify-0.1.0.dist-info/RECORD
